pcp_api/__init__.cpython-310-x86_64-linux-gnu.so
pcp_api/__init__.pyi
pcp_api/pcp.cpython-310-x86_64-linux-gnu.so
pcp_api/pcp_over_usb.cpython-310-x86_64-linux-gnu.so
pcp_api/pcp_over_usb.pyi
pcp_api/pulsar_actuator.cpython-310-x86_64-linux-gnu.so
pcp_api/pulsar_actuator.pyi
pcp_api/pulsar_cli.cpython-310-x86_64-linux-gnu.so
pcp_api/py.typed
pcp_api-0.9.6.dist-info/METADATA
pcp_api-0.9.6.dist-info/WHEEL
pcp_api-0.9.6.dist-info/entry_points.txt
pcp_api-0.9.6.dist-info/top_level.txt
pcp_api-0.9.6.dist-info/RECORD
