Metadata-Version: 2.4
Name: pcp_api
Version: 0.9.6
Summary: Python API for Pulsar PCP communication.
Author-email: Daniel Alvarez Eusebio <daeusebio@arquimea.com>
License: MIT
Project-URL: homepage, https://pulsarhri.com/
Classifier: Programming Language :: Python :: 3
Classifier: Operating System :: OS Independent
Requires-Python: >=3.7
Requires-Dist: pyserial>=3.5
